AUTHORS
LICENSE
MANIFEST.in
setup.py
django_jcrop/__init__.py
django_jcrop/forms.py
django_jcrop/models.py
django_jcrop/tests.py
django_jcrop/views.py
django_jcrop.egg-info/PKG-INFO
django_jcrop.egg-info/SOURCES.txt
django_jcrop.egg-info/dependency_links.txt
django_jcrop.egg-info/requires.txt
django_jcrop.egg-info/top_level.txt
django_jcrop/static/django_jcrop/css/Jcrop.gif
django_jcrop/static/django_jcrop/css/jcrop-widget.css
django_jcrop/static/django_jcrop/css/jquery.Jcrop.css
django_jcrop/static/django_jcrop/css/jquery.Jcrop.min.css
django_jcrop/static/django_jcrop/demos/demo_files/flowers.jpg
django_jcrop/static/django_jcrop/demos/demo_files/sago.jpg
django_jcrop/static/django_jcrop/demos/demo_files/sagomod.jpg
django_jcrop/static/django_jcrop/demos/demo_files/sagomod.png
django_jcrop/static/django_jcrop/js/jquery.Jcrop.js
django_jcrop/static/django_jcrop/js/jquery.Jcrop.min.js
django_jcrop/static/django_jcrop/js/jquery.color.js
django_jcrop/templates/jcrop/jcrop_image_widget.html