Metadata-Version: 1.1
Name: django-jcrop
Version: 0.0.2
Summary: ('Django app providing cropping functionnality with jcrop',)
Home-page: http://github.com/mauler/django-jcrop/
Author: Paulo R
Author-email: proberto@gmail.com
License: BSD
Platform: UNKNOWN
Classifier: Environment :: Web Environment
Classifier: Framework :: Django
Classifier: Intended Audience :: Developers
Classifier: License :: OSI Approved :: BSD License
Classifier: Operating System :: OS Independent
